sinr/__init__.py
sinr/graph_embeddings.py
sinr/how_to_install.md
sinr/logger.py
sinr/nfm.py
sinr/strategy_loader.py
sinr/text/__init__.py
sinr/text/config.json
sinr/text/config_fr.json
sinr/text/cooccurrence.py
sinr/text/cooccurrence_cython.pyx
sinr/text/diachrony.py
sinr/text/evaluate.py
sinr/text/exceptions_for_categorization.txt
sinr/text/exceptions_for_evaluation.txt
sinr/text/exceptions_for_similarity.txt
sinr/text/pmi.py
sinr/text/preprocess.py
sinr/viz.py
sinr-1.4.2.dist-info/METADATA
sinr-1.4.2.dist-info/WHEEL
sinr-1.4.2.dist-info/licenses/AUTHORS.rst
sinr-1.4.2.dist-info/licenses/LICENSE
sinr-1.4.2.dist-info/RECORD
