Metadata-Version: 2.4
Name: sinr
Version: 1.4.2
Summary: Build word and graph embeddings based on community detection in graphs.
License: CeCILL 2.1
License-File: AUTHORS.rst
License-File: LICENSE
Keywords: node embedding,word embedding,embedding,graph embedding,louvain,community
Author: Thibault Prouteau
Author-email: thibault.prouteau@univ-lemans.fr
Requires-Python: >=3.9,<3.13
Classifier: Development Status :: 4 - Beta
Classifier: Intended Audience :: Science/Research
Classifier: License :: Other/Proprietary License
Classifier: Operating System :: OS Independent
Classifier: Programming Language :: Cython
Classifier: Programming Language :: Python
Classifier: Programming Language :: Python :: 3
Classifier: Programming Language :: Python :: 3.9
Classifier: Programming Language :: Python :: 3.10
Classifier: Programming Language :: Python :: 3.11
Classifier: Programming Language :: Python :: 3.12
Classifier: Topic :: Scientific/Engineering
Classifier: Topic :: Software Development :: Libraries :: Python Modules
Provides-Extra: docs
Requires-Dist: docutils (==0.18.1)
Requires-Dist: igraph (>=0.10.4,<0.11.0)
Requires-Dist: ipykernel (>=6.21.1,<7.0.0)
Requires-Dist: joblib (>=1.1.1)
Requires-Dist: matplotlib (>=3.7.0,<4.0.0)
Requires-Dist: networkit (==11.0.1) ; python_version >= "3.11"
Requires-Dist: networkit (==9.1.1) ; python_version < "3.11"
Requires-Dist: numpy (>=1.20.0)
Requires-Dist: pandas (>=1.3.5)
Requires-Dist: scikit-learn (>=1.2.1,<2.0.0)
Requires-Dist: scipy (>=1.6.1)
Requires-Dist: spacy (==3.7.0)
Requires-Dist: tabulate (>=0.9.0,<0.10.0)
Requires-Dist: tqdm (>=4.64.1,<5.0.0)
Requires-Dist: xgboost (>=2.0.3,<3.0.0)
Project-URL: Homepage, https://sinr-embeddings.github.io/sinr/_build/html/index.html
Project-URL: Repository, https://github.com/SINr-Embeddings/sinr
